cards_rk/__init__.py
cards_rk/_modidx.py
cards_rk/card.py
cards_rk/deck.py
cards_rk-0.0.1.dist-info/LICENSE
cards_rk-0.0.1.dist-info/METADATA
cards_rk-0.0.1.dist-info/WHEEL
cards_rk-0.0.1.dist-info/entry_points.txt
cards_rk-0.0.1.dist-info/top_level.txt
cards_rk-0.0.1.dist-info/RECORD
